cellmetrik/__init__.py
cellmetrik/cellmetrik.py
cellmetrik/common.py
cellmetrik-0.0.1.dist-info/LICENSE
cellmetrik-0.0.1.dist-info/METADATA
cellmetrik-0.0.1.dist-info/WHEEL
cellmetrik-0.0.1.dist-info/entry_points.txt
cellmetrik-0.0.1.dist-info/top_level.txt
cellmetrik-0.0.1.dist-info/RECORD
