Metadata-Version: 2.1
Name: cellmetrik
Version: 0.0.1
Summary: Geometric manipulations on embeddings.
Author-email: Javier Ruiz-Ramirez <javier.ruizramirez@uhn.ca>
License: GNU General Public License v3
Project-URL: Homepage, https://github.com/JRR3/cellmetrik
Keywords: cellmetrik
Classifier: Intended Audience :: Developers
Classifier: Natural Language :: English
Classifier: Programming Language :: Python :: 3.9
Classifier: Programming Language :: Python :: 3.10
Classifier: Programming Language :: Python :: 3.11
Classifier: Programming Language :: Python :: 3.12
Requires-Python: >=3.9
License-File: LICENSE
Requires-Dist: numpy
Provides-Extra: all
Requires-Dist: cellmetrik[extra] ; extra == 'all'
Provides-Extra: extra
Requires-Dist: pandas ; extra == 'extra'
